captcha_crack/1.png
captcha_crack/2.png
captcha_crack/3.png
captcha_crack/4.png
captcha_crack/5.png
captcha_crack/6.png
captcha_crack/7.png
captcha_crack/8.png
captcha_crack/9.png
captcha_crack/A.png
captcha_crack/B.png
captcha_crack/C.png
captcha_crack/D.png
captcha_crack/E.png
captcha_crack/F.png
captcha_crack/G.png
captcha_crack/H.png
captcha_crack/I.png
captcha_crack/J.png
captcha_crack/K.png
captcha_crack/L.png
captcha_crack/M.png
captcha_crack/N.png
captcha_crack/P.png
captcha_crack/Q.png
captcha_crack/R.png
captcha_crack/S.png
captcha_crack/T.png
captcha_crack/U.png
captcha_crack/V.png
captcha_crack/W.png
captcha_crack/X.png
captcha_crack/Y.png
captcha_crack/Z.png
captcha_crack/__init__.py
captcha_crack/vtop.py
captcha_crack-0.1.dist-info/LICENSE
captcha_crack-0.1.dist-info/METADATA
captcha_crack-0.1.dist-info/WHEEL
captcha_crack-0.1.dist-info/top_level.txt
captcha_crack-0.1.dist-info/RECORD
