Metadata-Version: 2.1
Name: captcha-crack
Version: 0.1
Summary: A package to crack VTOPs captcha.
Home-page: https://github.com/deekay1712/vtop-captcha-crack
Author: Dikshansh Kumar Lodhi
Author-email: dikshansh1712@gmail.com
Classifier: Programming Language :: Python :: 3
Classifier: License :: OSI Approved :: MIT License
Classifier: Operating System :: OS Independent
Requires-Python: >=3.7
License-File: LICENSE
